pyrad2/__init__.py
pyrad2/bidict.py
pyrad2/client.py
pyrad2/client_async.py
pyrad2/constants.py
pyrad2/dictfile.py
pyrad2/dictionary.py
pyrad2/exceptions.py
pyrad2/host.py
pyrad2/packet.py
pyrad2/proxy.py
pyrad2/server.py
pyrad2/server_async.py
pyrad2/tools.py
pyrad2/radsec/__init__.py
pyrad2/radsec/client.py
pyrad2/radsec/server.py
pyrad2-1.1.1.dist-info/licenses/LICENSE.txt
pyrad2-1.1.1.dist-info/METADATA
pyrad2-1.1.1.dist-info/WHEEL
pyrad2-1.1.1.dist-info/top_level.txt
pyrad2-1.1.1.dist-info/zip-safe
pyrad2-1.1.1.dist-info/RECORD
