Metadata-Version: 2.4
Name: pyrad2
Version: 1.1.1
Summary: RADIUS Server
Home-page: https://github.com/nicholasamorim/pyrad2
Author: Nicholas Amorim, Istvan Ruzman, Christian Giese
Author-email: nicholas@santos.ee, istvan@ruzman.eu, developer@gicnet.de
Requires-Python: >=3.12
License-File: LICENSE.txt
Requires-Dist: loguru>=0.7.3
Requires-Dist: mkdocs-material>=9.6.15
Requires-Dist: mkdocstrings[python]>=0.29.1
Dynamic: author
Dynamic: author-email
Dynamic: home-page
Dynamic: license-file
